pms_onpremise_encoder/__init__.py
pms_onpremise_encoder/onpremise_encoder.py
pms_onpremise_encoder/common/__init__.py
pms_onpremise_encoder/common/_mysql_client.py
pms_onpremise_encoder/common/_redis_client.py
pms_onpremise_encoder/common/data_struct.py
pms_onpremise_encoder/encoder/__init__.py
pms_onpremise_encoder/encoder/_image_encoder.py
pms_onpremise_encoder/encoder/_video_encoder.py
pms_onpremise_encoder/encoder/processor/__init__.py
pms_onpremise_encoder/encoder/processor/_video_processor.py
pms_onpremise_encoder/encoder/redis/__init__.py
pms_onpremise_encoder/encoder/redis/_progress.py
pms_onpremise_encoder/encoder/repository/__init__.py
pms_onpremise_encoder/encoder/repository/_file_status_repo.py
pms_onpremise_encoder/encoder/repository/_video_meta_repo.py
pms_onpremise_encoder/encoder/utils/__init__.py
pms_onpremise_encoder/encoder/utils/_calculate_progress.py
pms_onpremise_encoder/encoder/utils/_delete_file_util.py
pms_onpremise_encoder/encoder/utils/_queue_object_generator.py
pms_onpremise_encoder/encoder/utils/_sub_output_util.py
pms_onpremise_encoder/encoder/utils/_video_ffmpeg_cmd_generator.py
pms_onpremise_encoder-0.0.13.dist-info/METADATA
pms_onpremise_encoder-0.0.13.dist-info/WHEEL
pms_onpremise_encoder-0.0.13.dist-info/top_level.txt
pms_onpremise_encoder-0.0.13.dist-info/RECORD
